pysurvive/CustomLibraryLoader.py
pysurvive/__init__.py
pysurvive/__main__.py
pysurvive/libsurvive.dll
pysurvive/pysurvive_generated.py
pysurvive/recorder.py
pysurvive/survive.lib
pysurvive/images/config_icon.png
pysurvive/images/program_icon.png
pysurvive/images/running_icon.png
pysurvive/libsurvive/plugins/disambiguator_statebased.dll
pysurvive/libsurvive/plugins/disambiguator_statebased.lib
pysurvive/libsurvive/plugins/driver_dummy.dll
pysurvive/libsurvive/plugins/driver_dummy.lib
pysurvive/libsurvive/plugins/driver_global_scene_solver.dll
pysurvive/libsurvive/plugins/driver_global_scene_solver.lib
pysurvive/libsurvive/plugins/driver_playback.dll
pysurvive/libsurvive/plugins/driver_playback.lib
pysurvive/libsurvive/plugins/driver_simulator.dll
pysurvive/libsurvive/plugins/driver_simulator.lib
pysurvive/libsurvive/plugins/driver_vive.dll
pysurvive/libsurvive/plugins/driver_vive.lib
pysurvive/libsurvive/plugins/poser_barycentric_svd.dll
pysurvive/libsurvive/plugins/poser_barycentric_svd.lib
pysurvive/libsurvive/plugins/poser_dummy.dll
pysurvive/libsurvive/plugins/poser_dummy.lib
pysurvive/libsurvive/plugins/poser_kalman_only.dll
pysurvive/libsurvive/plugins/poser_kalman_only.lib
pysurvive/libsurvive/plugins/poser_mpfit.dll
pysurvive/libsurvive/plugins/poser_mpfit.lib
pysurvive-1.1.23.data/data/bin/Demo.deps.json
pysurvive-1.1.23.data/data/bin/Demo.dll
pysurvive-1.1.23.data/data/bin/Demo.dll.config
pysurvive-1.1.23.data/data/bin/Demo.pdb
pysurvive-1.1.23.data/data/bin/Demo.runtimeconfig.dev.json
pysurvive-1.1.23.data/data/bin/Demo.runtimeconfig.json
pysurvive-1.1.23.data/data/bin/libsurvive.net.dll
pysurvive-1.1.23.data/data/bin/x64/survive-cli.exe
pysurvive-1.1.23.data/data/bin/x64/survive-websocketd.ps1
pysurvive-1.1.23.data/data/include/cnkalman/ModelPlot.h
pysurvive-1.1.23.data/data/include/cnkalman/generated_header.h
pysurvive-1.1.23.data/data/include/cnkalman/kalman.h
pysurvive-1.1.23.data/data/include/cnkalman/model.h
pysurvive-1.1.23.dist-info/LICENSE
pysurvive-1.1.23.dist-info/METADATA
pysurvive-1.1.23.dist-info/WHEEL
pysurvive-1.1.23.dist-info/top_level.txt
pysurvive-1.1.23.dist-info/RECORD
