Metadata-Version: 2.1
Name: pysurvive
Version: 1.1.23
Summary: Libsurvive is a set of tools and libraries that enable 6 dof tracking on lighthouse and vive based systems that is completely open source and can run on any device. It currently supports both SteamVR 1.0 and SteamVR 2.0 generation of devices and should support any tracked object commercially available.
Home-page: https://github.com/cntools/libsurvive
License: MIT
Platform: UNKNOWN
License-File: LICENSE
Requires-Dist: gooey
